sbmlnetwork/__init__.py
sbmlnetwork/sbmlnetwork.py
sbmlnetwork/settings.py
sbmlnetwork/features/__init__.py
sbmlnetwork/features/align.py
sbmlnetwork/features/data_integration.py
sbmlnetwork/features/grouping.py
sbmlnetwork/features/color_bar/__init__.py
sbmlnetwork/features/color_bar/color_bar.py
sbmlnetwork/features/color_bar/color_bar_manager.py
sbmlnetwork/features/styles/__init__.py
sbmlnetwork/features/styles/style_manager.py
sbmlnetwork/network_elements/__init__.py
sbmlnetwork/network_elements/additional_element.py
sbmlnetwork/network_elements/compartment.py
sbmlnetwork/network_elements/network_element_base.py
sbmlnetwork/network_elements/reaction.py
sbmlnetwork/network_elements/species.py
sbmlnetwork/network_elements/network_element_lists/__init__.py
sbmlnetwork/network_elements/network_element_lists/additional_element_list.py
sbmlnetwork/network_elements/network_element_lists/compartment_list.py
sbmlnetwork/network_elements/network_element_lists/network_element_base_list.py
sbmlnetwork/network_elements/network_element_lists/reaction_list.py
sbmlnetwork/network_elements/network_element_lists/species_list.py
sbmlnetwork/network_elements/visual_elements/__init__.py
sbmlnetwork/network_elements/visual_elements/label.py
sbmlnetwork/network_elements/visual_elements/reaction_center.py
sbmlnetwork/network_elements/visual_elements/curve/__init__.py
sbmlnetwork/network_elements/visual_elements/curve/arrow_head.py
sbmlnetwork/network_elements/visual_elements/curve/curve.py
sbmlnetwork/network_elements/visual_elements/curve/curve_segment.py
sbmlnetwork/network_elements/visual_elements/shapes/__init__.py
sbmlnetwork/network_elements/visual_elements/shapes/curve.py
sbmlnetwork/network_elements/visual_elements/shapes/ellipse.py
sbmlnetwork/network_elements/visual_elements/shapes/polygon.py
sbmlnetwork/network_elements/visual_elements/shapes/rectangle.py
sbmlnetwork/network_elements/visual_elements/shapes/shape_base.py
sbmlnetwork-0.5.12.dist-info/LICENSE
sbmlnetwork-0.5.12.dist-info/METADATA
sbmlnetwork-0.5.12.dist-info/WHEEL
sbmlnetwork-0.5.12.dist-info/top_level.txt
sbmlnetwork-0.5.12.dist-info/RECORD
