Metadata-Version: 2.1
Name: sbmlnetwork
Version: 0.5.12
Summary: A python api to work with libsbmlnetwork library
Home-page: https://github.com/adelhpour/SBMLNetwork
Author: Adel Heydarabadipour
Author-email: adelhp@uw.edu
Project-URL: Bug Tracker, https://github.com/adelhpour/SBMLNetwork/issues
Classifier: Programming Language :: Python :: 3
Classifier: License :: OSI Approved :: MIT License
Classifier: Operating System :: OS Independent
Requires-Python: >=3.9
License-File: LICENSE
Requires-Dist: libsbmlnetwork>=0.5.12
Requires-Dist: networkinfotranslator>=0.5.12
Requires-Dist: pillow
Requires-Dist: matplotlib
Provides-Extra: all
Requires-Dist: tellurium; extra == "all"
Provides-Extra: tellurium
Requires-Dist: tellurium; extra == "tellurium"
